ZenithTA-1.0.0.dist-info/METADATA
ZenithTA-1.0.0.dist-info/WHEEL
ZenithTA-1.0.0.dist-info/license_files/LICENSE
ZenithTA/__init__.py
ZenithTA/ZenithTA.abi3.so
ZenithTA-1.0.0.dist-info/RECORD
