Metadata-Version: 2.1
Name: ZenithTA
Version: 1.0.0
Requires-Dist: numpy
License-File: LICENSE
